{"name":"SampleScene","frame_height":8.0,"frame_width":6.378167629241943,"spriteLayoutStructs":[{"id":-11228,"object_name":"pinball_side_bumper (1)","texture_name":"pinball_sprite","sprite_name":"pinball_side_bumper","x":3.2300000190734865,"y":2.140000104904175,"scale_x":1.5,"scale_y":1.5,"rotation":-0.7068583965301514,"flip_x":-1,"flip_y":1,"tag":10,"properties":"","collisionStruct":{"collisionType":0,"data":"{\"point_a\":{\"x\":-0.1599999964237213,\"y\":-0.4000000059604645},\"point_b\":{\"x\":-0.15000000596046449,\"y\":0.3499999940395355}}"},"constraintStruct":{"max_rotation":0.0,"min_rotation":0.0,"rest_point":0.0,"max_x":0.0,"min_x":0.0,"rest_x":0.0,"max_y":0.0,"min_y":0.0,"rest_y":0.0}},{"id":-4358,"object_name":"pinball (16)","texture_name":"pinball_sprite","sprite_name":"pinball","x":1.809999942779541,"y":3.6700000762939455,"scale_x":0.4000000059604645,"scale_y":0.4000000059604645,"rotation":0.0,"flip_x":1,"flip_y":1,"tag":8,"properties":"","collisionStruct":{"collisionType":3,"data":"{\"x\":0.0,\"y\":0.0,\"radius\":0.12999999523162843}"},"constraintStruct":{"max_rotation":0.0,"min_rotation":0.0,"rest_point":0.0,"max_x":0.0,"min_x":0.0,"rest_x":0.0,"max_y":0.0,"min_y":0.0,"rest_y":0.0}},{"id":-4276,"object_name":"pinball (15)","texture_name":"pinball_sprite","sprite_name":"pinball","x":1.5199999809265137,"y":2.869999885559082,"scale_x":0.4000000059604645,"scale_y":0.4000000059604645,"rotation":0.0,"flip_x":1,"flip_y":1,"tag":8,"properties":"","collisionStruct":{"collisionType":3,"data":"{\"x\":0.0,\"y\":0.0,\"radius\":0.12999999523162843}"},"constraintStruct":{"max_rotation":0.0,"min_rotation":0.0,"rest_point":0.0,"max_x":0.0,"min_x":0.0,"rest_x":0.0,"max_y":0.0,"min_y":0.0,"rest_y":0.0}},{"id":-4082,"object_name":"pinball (14)","texture_name":"pinball_sprite","sprite_name":"pinball","x":-0.38999998569488528,"y":3.6500000953674318,"scale_x":0.4000000059604645,"scale_y":0.4000000059604645,"rotation":0.0,"flip_x":1,"flip_y":1,"tag":8,"properties":"","collisionStruct":{"collisionType":3,"data":"{\"x\":0.0,\"y\":0.0,\"radius\":0.12999999523162843}"},"constraintStruct":{"max_rotation":0.0,"min_rotation":0.0,"rest_point":0.0,"max_x":0.0,"min_x":0.0,"rest_x":0.0,"max_y":0.0,"min_y":0.0,"rest_y":0.0}},{"id":-4022,"object_name":"pinball (13)","texture_name":"pinball_sprite","sprite_name":"pinball","x":1.6299999952316285,"y":1.7100000381469727,"scale_x":0.4000000059604645,"scale_y":0.4000000059604645,"rotation":0.0,"flip_x":1,"flip_y":1,"tag":8,"properties":"","collisionStruct":{"collisionType":3,"data":"{\"x\":0.0,\"y\":0.0,\"radius\":0.12999999523162843}"},"constraintStruct":{"max_rotation":0.0,"min_rotation":0.0,"rest_point":0.0,"max_x":0.0,"min_x":0.0,"rest_x":0.0,"max_y":0.0,"min_y":0.0,"rest_y":0.0}},{"id":-3938,"object_name":"pinball (12)","texture_name":"pinball_sprite","sprite_name":"pinball","x":0.7200000286102295,"y":-0.5099999904632568,"scale_x":0.4000000059604645,"scale_y":0.4000000059604645,"rotation":0.0,"flip_x":1,"flip_y":1,"tag":8,"properties":"","collisionStruct":{"collisionType":3,"data":"{\"x\":0.0,\"y\":0.0,\"radius\":0.12999999523162843}"},"constraintStruct":{"max_rotation":0.0,"min_rotation":0.0,"rest_point":0.0,"max_x":0.0,"min_x":0.0,"rest_x":0.0,"max_y":0.0,"min_y":0.0,"rest_y":0.0}},{"id":-3848,"object_name":"pinball (11)","texture_name":"pinball_sprite","sprite_name":"pinball","x":-0.4699999988079071,"y":-2.809999942779541,"scale_x":0.4000000059604645,"scale_y":0.4000000059604645,"rotation":0.0,"flip_x":1,"flip_y":1,"tag":8,"properties":"","collisionStruct":{"collisionType":3,"data":"{\"x\":0.0,\"y\":0.0,\"radius\":0.12999999523162843}"},"constraintStruct":{"max_rotation":0.0,"min_rotation":0.0,"rest_point":0.0,"max_x":0.0,"min_x":0.0,"rest_x":0.0,"max_y":0.0,"min_y":0.0,"rest_y":0.0}},{"id":-3764,"object_name":"pinball (10)","texture_name":"pinball_sprite","sprite_name":"pinball","x":-1.2599999904632569,"y":2.6700000762939455,"scale_x":0.4000000059604645,"scale_y":0.4000000059604645,"rotation":0.0,"flip_x":1,"flip_y":1,"tag":8,"properties":"","collisionStruct":{"collisionType":3,"data":"{\"x\":0.0,\"y\":0.0,\"radius\":0.12999999523162843}"},"constraintStruct":{"max_rotation":0.0,"min_rotation":0.0,"rest_point":0.0,"max_x":0.0,"min_x":0.0,"rest_x":0.0,"max_y":0.0,"min_y":0.0,"rest_y":0.0}},{"id":-3690,"object_name":"pinball (9)","texture_name":"pinball_sprite","sprite_name":"pinball","x":-0.6899999976158142,"y":-2.259999990463257,"scale_x":0.4000000059604645,"scale_y":0.4000000059604645,"rotation":0.0,"flip_x":1,"flip_y":1,"tag":8,"properties":"","collisionStruct":{"collisionType":3,"data":"{\"x\":0.0,\"y\":0.0,\"radius\":0.12999999523162843}"},"constraintStruct":{"max_rotation":0.0,"min_rotation":0.0,"rest_point":0.0,"max_x":0.0,"min_x":0.0,"rest_x":0.0,"max_y":0.0,"min_y":0.0,"rest_y":0.0}},{"id":-3608,"object_name":"pinball (8)","texture_name":"pinball_sprite","sprite_name":"pinball","x":0.6800000071525574,"y":-2.5199999809265138,"scale_x":0.4000000059604645,"scale_y":0.4000000059604645,"rotation":0.0,"flip_x":1,"flip_y":1,"tag":8,"properties":"","collisionStruct":{"collisionType":3,"data":"{\"x\":0.0,\"y\":0.0,\"radius\":0.12999999523162843}"},"constraintStruct":{"max_rotation":0.0,"min_rotation":0.0,"rest_point":0.0,"max_x":0.0,"min_x":0.0,"rest_x":0.0,"max_y":0.0,"min_y":0.0,"rest_y":0.0}},{"id":-3514,"object_name":"pinball (7)","texture_name":"pinball_sprite","sprite_name":"pinball","x":2.130000114440918,"y":3.049999952316284,"scale_x":0.4000000059604645,"scale_y":0.4000000059604645,"rotation":0.0,"flip_x":1,"flip_y":1,"tag":8,"properties":"","collisionStruct":{"collisionType":3,"data":"{\"x\":0.0,\"y\":0.0,\"radius\":0.12999999523162843}"},"constraintStruct":{"max_rotation":0.0,"min_rotation":0.0,"rest_point":0.0,"max_x":0.0,"min_x":0.0,"rest_x":0.0,"max_y":0.0,"min_y":0.0,"rest_y":0.0}},{"id":-3414,"object_name":"pinball (6)","texture_name":"pinball_sprite","sprite_name":"pinball","x":0.47999998927116396,"y":3.6700000762939455,"scale_x":0.4000000059604645,"scale_y":0.4000000059604645,"rotation":0.0,"flip_x":1,"flip_y":1,"tag":8,"properties":"","collisionStruct":{"collisionType":3,"data":"{\"x\":0.0,\"y\":0.0,\"radius\":0.12999999523162843}"},"constraintStruct":{"max_rotation":0.0,"min_rotation":0.0,"rest_point":0.0,"max_x":0.0,"min_x":0.0,"rest_x":0.0,"max_y":0.0,"min_y":0.0,"rest_y":0.0}},{"id":-3144,"object_name":"pinball (5)","texture_name":"pinball_sprite","sprite_name":"pinball","x":-0.8899999856948853,"y":2.809999942779541,"scale_x":0.4000000059604645,"scale_y":0.4000000059604645,"rotation":0.0,"flip_x":1,"flip_y":1,"tag":8,"properties":"","collisionStruct":{"collisionType":3,"data":"{\"x\":0.0,\"y\":0.0,\"radius\":0.12999999523162843}"},"constraintStruct":{"max_rotation":0.0,"min_rotation":0.0,"rest_point":0.0,"max_x":0.0,"min_x":0.0,"rest_x":0.0,"max_y":0.0,"min_y":0.0,"rest_y":0.0}},{"id":30982,"object_name":"pinball_wall (4)","texture_name":"pinball_sprite","sprite_name":"pinball_wall","x":2.7230000495910646,"y":-1.4660000801086426,"scale_x":1.0,"scale_y":1.0,"rotation":0.0,"flip_x":1,"flip_y":1,"tag":0,"properties":"","collisionStruct":{"collisionType":0,"data":""},"constraintStruct":{"max_rotation":0.0,"min_rotation":0.0,"rest_point":0.0,"max_x":0.0,"min_x":0.0,"rest_x":0.0,"max_y":0.0,"min_y":0.0,"rest_y":0.0}},{"id":30990,"object_name":"pinball_bumper","texture_name":"pinball_sprite","sprite_name":"pinball_bumper","x":-0.8700000643730164,"y":1.9800002574920655,"scale_x":1.5,"scale_y":1.5,"rotation":0.0,"flip_x":1,"flip_y":1,"tag":9,"properties":"{\r\"Friend\":\"dsd\",\r\"dsd\":33,\r\"ee\":[\r\"dd\"\r]\r}","collisionStruct":{"collisionType":3,"data":"{\"x\":0.0,\"y\":0.0,\"radius\":0.4000000059604645}"},"constraintStruct":{"max_rotation":0.0,"min_rotation":0.0,"rest_point":0.0,"max_x":0.0,"min_x":0.0,"rest_x":0.0,"max_y":0.0,"min_y":0.0,"rest_y":0.0}},{"id":31000,"object_name":"pinball_flipper_left","texture_name":"pinball_sprite","sprite_name":"pinball_flipper","x":-1.0,"y":-3.0,"scale_x":1.5,"scale_y":1.5,"rotation":-5.93411922454834,"flip_x":1,"flip_y":1,"tag":6,"properties":"{\r\"max_rotation\":0.523\r}","collisionStruct":{"collisionType":2,"data":"{\"sphere_a\":{\"x\":0.14000000059604646,\"y\":-0.019999999552965165,\"radius\":0.18000000715255738},\"sphere_b\":{\"x\":0.6700000166893005,\"y\":-0.029999999329447748,\"radius\":0.10000000149011612}}"},"constraintStruct":{"max_rotation":0.3490658402442932,"min_rotation":-0.3490658402442932,"rest_point":0.3490658402442932,"max_x":0.0,"min_x":0.0,"rest_x":0.0,"max_y":0.0,"min_y":0.0,"rest_y":0.0}},{"id":31016,"object_name":"pinball_cuve","texture_name":"pinball_sprite","sprite_name":"pinball_cuve","x":2.052999973297119,"y":0.4139997959136963,"scale_x":1.0,"scale_y":1.0,"rotation":0.0,"flip_x":1,"flip_y":1,"tag":0,"properties":"","collisionStruct":{"collisionType":4,"data":"{\"points\":[{\"x\":0.0,\"y\":0.0},{\"x\":0.0,\"y\":1.0}]}"},"constraintStruct":{"max_rotation":0.0,"min_rotation":0.0,"rest_point":0.0,"max_x":0.0,"min_x":0.0,"rest_x":0.0,"max_y":0.0,"min_y":0.0,"rest_y":0.0}},{"id":31026,"object_name":"pinball_side_bumper","texture_name":"pinball_sprite","sprite_name":"pinball_side_bumper","x":1.0,"y":-1.0,"scale_x":1.5,"scale_y":1.5,"rotation":-5.93411922454834,"flip_x":-1,"flip_y":1,"tag":10,"properties":"","collisionStruct":{"collisionType":0,"data":"{\"point_a\":{\"x\":-0.1599999964237213,\"y\":-0.4000000059604645},\"point_b\":{\"x\":-0.15000000596046449,\"y\":0.3499999940395355}}"},"constraintStruct":{"max_rotation":0.0,"min_rotation":0.0,"rest_point":0.0,"max_x":0.0,"min_x":0.0,"rest_x":0.0,"max_y":0.0,"min_y":0.0,"rest_y":0.0}},{"id":31036,"object_name":"pinball (4)","texture_name":"pinball_sprite","sprite_name":"pinball","x":3.031100034713745,"y":-3.0018999576568605,"scale_x":0.4000000059604645,"scale_y":0.4000000059604645,"rotation":0.0,"flip_x":1,"flip_y":1,"tag":8,"properties":"","collisionStruct":{"collisionType":3,"data":"{\"x\":0.0,\"y\":0.0,\"radius\":0.12999999523162843}"},"constraintStruct":{"max_rotation":0.0,"min_rotation":0.0,"rest_point":0.0,"max_x":0.0,"min_x":0.0,"rest_x":0.0,"max_y":0.0,"min_y":0.0,"rest_y":0.0}},{"id":31046,"object_name":"pinball","texture_name":"pinball_sprite","sprite_name":"pinball","x":-0.800000011920929,"y":-0.5,"scale_x":0.4000000059604645,"scale_y":0.4000000059604645,"rotation":0.0,"flip_x":1,"flip_y":1,"tag":8,"properties":"","collisionStruct":{"collisionType":3,"data":"{\"x\":0.0,\"y\":0.0,\"radius\":0.12999999523162843}"},"constraintStruct":{"max_rotation":0.0,"min_rotation":0.0,"rest_point":0.0,"max_x":0.0,"min_x":0.0,"rest_x":0.0,"max_y":0.0,"min_y":0.0,"rest_y":0.0}},{"id":31056,"object_name":"pinball_bumper (1)","texture_name":"pinball_sprite","sprite_name":"pinball_bumper","x":0.07999996840953827,"y":3.189000129699707,"scale_x":1.5,"scale_y":1.5,"rotation":0.0,"flip_x":1,"flip_y":1,"tag":9,"properties":"{\r\"Friend\":\"dsd\",\r\"dsd\":33,\r\"ee\":[\r\"dd\"\r]\r}","collisionStruct":{"collisionType":3,"data":"{\"x\":0.0,\"y\":0.0,\"radius\":0.4000000059604645}"},"constraintStruct":{"max_rotation":0.0,"min_rotation":0.0,"rest_point":0.0,"max_x":0.0,"min_x":0.0,"rest_x":0.0,"max_y":0.0,"min_y":0.0,"rest_y":0.0}},{"id":31066,"object_name":"side_boundary","texture_name":"","sprite_name":"","x":0.8190000057220459,"y":-1.1200000047683716,"scale_x":1.0,"scale_y":1.0,"rotation":0.0,"flip_x":0,"flip_y":0,"tag":0,"properties":"","collisionStruct":{"collisionType":2,"data":"{\"sphere_a\":{\"x\":-0.05000000074505806,\"y\":-0.20999999344348908,\"radius\":0.05000000074505806},\"sphere_b\":{\"x\":0.3799999952316284,\"y\":-0.009999999776482582,\"radius\":0.05000000074505806}}"},"constraintStruct":{"max_rotation":0.0,"min_rotation":0.0,"rest_point":0.0,"max_x":0.0,"min_x":0.0,"rest_x":0.0,"max_y":0.0,"min_y":0.0,"rest_y":0.0}},{"id":31074,"object_name":"pinball_shooter","texture_name":"pinball_sprite","sprite_name":"pinball_shooter","x":3.052999973297119,"y":-4.0,"scale_x":1.7999999523162842,"scale_y":1.600000023841858,"rotation":0.0,"flip_x":1,"flip_y":1,"tag":11,"properties":"","collisionStruct":{"collisionType":2,"data":"{\"sphere_a\":{\"x\":-0.019999999552965165,\"y\":0.7200000286102295,\"radius\":0.14000000059604646},\"sphere_b\":{\"x\":-0.019999999552965165,\"y\":0.10000000149011612,\"radius\":0.14000000059604646}}"},"constraintStruct":{"max_rotation":0.0,"min_rotation":0.0,"rest_point":0.0,"max_x":0.0,"min_x":0.0,"rest_x":0.0,"max_y":0.0,"min_y":-0.6000000238418579,"rest_y":0.0}},{"id":31094,"object_name":"pinball_flipper_right","texture_name":"pinball_sprite","sprite_name":"pinball_flipper","x":1.0,"y":-3.0,"scale_x":1.5,"scale_y":1.5,"rotation":-0.3490658104419708,"flip_x":-1,"flip_y":1,"tag":7,"properties":"{\r\"max_rotation\":-0.523\r}","collisionStruct":{"collisionType":2,"data":"{\"sphere_a\":{\"x\":-0.15000000596046449,\"y\":-0.009999999776482582,\"radius\":0.18000000715255738},\"sphere_b\":{\"x\":-0.6600000262260437,\"y\":-0.009999999776482582,\"radius\":0.10000000149011612}}"},"constraintStruct":{"max_rotation":0.3490658402442932,"min_rotation":-0.3490658402442932,"rest_point":-0.3490658402442932,"max_x":0.0,"min_x":0.0,"rest_x":0.0,"max_y":0.0,"min_y":0.0,"rest_y":0.0}},{"id":31106,"object_name":"side_boundary","texture_name":"","sprite_name":"","x":-1.1800000667572022,"y":-1.11899995803833,"scale_x":1.0,"scale_y":1.0,"rotation":0.0,"flip_x":0,"flip_y":0,"tag":0,"properties":"","collisionStruct":{"collisionType":2,"data":"{\"sphere_a\":{\"x\":0.0,\"y\":0.0,\"radius\":0.05000000074505806},\"sphere_b\":{\"x\":0.15000000596046449,\"y\":0.44999998807907107,\"radius\":0.05000000074505806}}"},"constraintStruct":{"max_rotation":0.0,"min_rotation":0.0,"rest_point":0.0,"max_x":0.0,"min_x":0.0,"rest_x":0.0,"max_y":0.0,"min_y":0.0,"rest_y":0.0}},{"id":31114,"object_name":"right_boundary_wall","texture_name":"","sprite_name":"","x":2.7230000495910646,"y":-3.996000051498413,"scale_x":1.0,"scale_y":1.0,"rotation":0.0,"flip_x":0,"flip_y":0,"tag":0,"properties":"","collisionStruct":{"collisionType":2,"data":"{\"sphere_a\":{\"x\":0.0,\"y\":4.929999828338623,\"radius\":0.15000000596046449},\"sphere_b\":{\"x\":0.0,\"y\":0.0,\"radius\":0.15000000596046449}}"},"constraintStruct":{"max_rotation":0.0,"min_rotation":0.0,"rest_point":0.0,"max_x":0.0,"min_x":0.0,"rest_x":0.0,"max_y":0.0,"min_y":0.0,"rest_y":0.0}},{"id":31122,"object_name":"pinball_wall (6)","texture_name":"pinball_sprite","sprite_name":"pinball_wall","x":2.7230000495910646,"y":-0.18000006675720216,"scale_x":1.0,"scale_y":1.0,"rotation":0.0,"flip_x":1,"flip_y":1,"tag":0,"properties":"","collisionStruct":{"collisionType":0,"data":""},"constraintStruct":{"max_rotation":0.0,"min_rotation":0.0,"rest_point":0.0,"max_x":0.0,"min_x":0.0,"rest_x":0.0,"max_y":0.0,"min_y":0.0,"rest_y":0.0}},{"id":31130,"object_name":"pinball_wall (7)","texture_name":"pinball_sprite","sprite_name":"pinball_wall","x":2.7230000495910646,"y":0.4440000057220459,"scale_x":1.0,"scale_y":1.0,"rotation":0.0,"flip_x":1,"flip_y":1,"tag":0,"properties":"","collisionStruct":{"collisionType":0,"data":""},"constraintStruct":{"max_rotation":0.0,"min_rotation":0.0,"rest_point":0.0,"max_x":0.0,"min_x":0.0,"rest_x":0.0,"max_y":0.0,"min_y":0.0,"rest_y":0.0}},{"id":31138,"object_name":"side_boundary","texture_name":"","sprite_name":"","x":-1.180999994277954,"y":-1.1200000047683716,"scale_x":1.0,"scale_y":1.0,"rotation":0.0,"flip_x":0,"flip_y":0,"tag":0,"properties":"","collisionStruct":{"collisionType":2,"data":"{\"sphere_a\":{\"x\":0.0,\"y\":0.0,\"radius\":0.05000000074505806},\"sphere_b\":{\"x\":0.38999998569488528,\"y\":-0.20999999344348908,\"radius\":0.05000000074505806}}"},"constraintStruct":{"max_rotation":0.0,"min_rotation":0.0,"rest_point":0.0,"max_x":0.0,"min_x":0.0,"rest_x":0.0,"max_y":0.0,"min_y":0.0,"rest_y":0.0}},{"id":31146,"object_name":"pinball_wall (2)","texture_name":"pinball_sprite","sprite_name":"pinball_wall","x":2.7230000495910646,"y":-2.7100000381469728,"scale_x":1.0,"scale_y":1.0,"rotation":0.0,"flip_x":1,"flip_y":1,"tag":0,"properties":"","collisionStruct":{"collisionType":0,"data":""},"constraintStruct":{"max_rotation":0.0,"min_rotation":0.0,"rest_point":0.0,"max_x":0.0,"min_x":0.0,"rest_x":0.0,"max_y":0.0,"min_y":0.0,"rest_y":0.0}},{"id":31154,"object_name":"pinball (2)","texture_name":"pinball_sprite","sprite_name":"pinball","x":0.029999999329447748,"y":3.809999942779541,"scale_x":0.4000000059604645,"scale_y":0.4000000059604645,"rotation":0.0,"flip_x":1,"flip_y":1,"tag":8,"properties":"","collisionStruct":{"collisionType":3,"data":"{\"x\":0.0,\"y\":0.0,\"radius\":0.12999999523162843}"},"constraintStruct":{"max_rotation":0.0,"min_rotation":0.0,"rest_point":0.0,"max_x":0.0,"min_x":0.0,"rest_x":0.0,"max_y":0.0,"min_y":0.0,"rest_y":0.0}},{"id":31164,"object_name":"pinball_wall (5)","texture_name":"pinball_sprite","sprite_name":"pinball_wall","x":2.7230000495910646,"y":-0.8280000686645508,"scale_x":1.0,"scale_y":1.0,"rotation":0.0,"flip_x":1,"flip_y":1,"tag":0,"properties":"","collisionStruct":{"collisionType":0,"data":""},"constraintStruct":{"max_rotation":0.0,"min_rotation":0.0,"rest_point":0.0,"max_x":0.0,"min_x":0.0,"rest_x":0.0,"max_y":0.0,"min_y":0.0,"rest_y":0.0}},{"id":31172,"object_name":"side_boundary","texture_name":"","sprite_name":"","x":0.8199999928474426,"y":-1.11899995803833,"scale_x":1.0,"scale_y":1.0,"rotation":0.0,"flip_x":0,"flip_y":0,"tag":0,"properties":"","collisionStruct":{"collisionType":2,"data":"{\"sphere_a\":{\"x\":0.3799999952316284,\"y\":0.0,\"radius\":0.05000000074505806},\"sphere_b\":{\"x\":0.20000000298023225,\"y\":0.44999998807907107,\"radius\":0.05000000074505806}}"},"constraintStruct":{"max_rotation":0.0,"min_rotation":0.0,"rest_point":0.0,"max_x":0.0,"min_x":0.0,"rest_x":0.0,"max_y":0.0,"min_y":0.0,"rest_y":0.0}},{"id":31180,"object_name":"pinball_bumper (2)","texture_name":"pinball_sprite","sprite_name":"pinball_bumper","x":1.9249999523162842,"y":2.3239998817443849,"scale_x":1.5,"scale_y":1.5,"rotation":0.0,"flip_x":1,"flip_y":1,"tag":9,"properties":"{\r\"Friend\":\"dsd\",\r\"dsd\":33,\r\"ee\":[\r\"dd\"\r]\r}","collisionStruct":{"collisionType":3,"data":"{\"x\":0.0,\"y\":0.0,\"radius\":0.4000000059604645}"},"constraintStruct":{"max_rotation":0.0,"min_rotation":0.0,"rest_point":0.0,"max_x":0.0,"min_x":0.0,"rest_x":0.0,"max_y":0.0,"min_y":0.0,"rest_y":0.0}},{"id":31194,"object_name":"pinball_wall","texture_name":"pinball_sprite","sprite_name":"pinball_wall","x":2.7230000495910646,"y":-3.996000051498413,"scale_x":1.0,"scale_y":1.0,"rotation":0.0,"flip_x":1,"flip_y":1,"tag":0,"properties":"","collisionStruct":{"collisionType":0,"data":""},"constraintStruct":{"max_rotation":0.0,"min_rotation":0.0,"rest_point":0.0,"max_x":0.0,"min_x":0.0,"rest_x":0.0,"max_y":0.0,"min_y":0.0,"rest_y":0.0}},{"id":31202,"object_name":"pinball_wall (3)","texture_name":"pinball_sprite","sprite_name":"pinball_wall","x":2.7230000495910646,"y":-2.0859999656677248,"scale_x":1.0,"scale_y":1.0,"rotation":0.0,"flip_x":1,"flip_y":1,"tag":0,"properties":"","collisionStruct":{"collisionType":0,"data":""},"constraintStruct":{"max_rotation":0.0,"min_rotation":0.0,"rest_point":0.0,"max_x":0.0,"min_x":0.0,"rest_x":0.0,"max_y":0.0,"min_y":0.0,"rest_y":0.0}},{"id":31210,"object_name":"pinball_side_bumper","texture_name":"pinball_sprite","sprite_name":"pinball_side_bumper","x":-1.0,"y":-1.0,"scale_x":1.5,"scale_y":1.5,"rotation":-0.3490658104419708,"flip_x":1,"flip_y":1,"tag":10,"properties":"","collisionStruct":{"collisionType":0,"data":"{\"point_a\":{\"x\":0.14000000059604646,\"y\":0.30000001192092898},\"point_b\":{\"x\":0.14000000059604646,\"y\":-0.3700000047683716}}"},"constraintStruct":{"max_rotation":0.0,"min_rotation":0.0,"rest_point":0.0,"max_x":0.0,"min_x":0.0,"rest_x":0.0,"max_y":0.0,"min_y":0.0,"rest_y":0.0}},{"id":31220,"object_name":"pinball_wall (1)","texture_name":"pinball_sprite","sprite_name":"pinball_wall","x":2.7230000495910646,"y":-3.3580000400543215,"scale_x":1.0,"scale_y":1.0,"rotation":0.0,"flip_x":1,"flip_y":1,"tag":0,"properties":"","collisionStruct":{"collisionType":0,"data":""},"constraintStruct":{"max_rotation":0.0,"min_rotation":0.0,"rest_point":0.0,"max_x":0.0,"min_x":0.0,"rest_x":0.0,"max_y":0.0,"min_y":0.0,"rest_y":0.0}}]}